blooio/__init__.py
blooio/_base_client.py
blooio/_client.py
blooio/_compat.py
blooio/_constants.py
blooio/_exceptions.py
blooio/_files.py
blooio/_models.py
blooio/_qs.py
blooio/_resource.py
blooio/_response.py
blooio/_streaming.py
blooio/_types.py
blooio/_version.py
blooio/py.typed
blooio/_utils/__init__.py
blooio/_utils/_compat.py
blooio/_utils/_datetime_parse.py
blooio/_utils/_logs.py
blooio/_utils/_proxy.py
blooio/_utils/_reflection.py
blooio/_utils/_resources_proxy.py
blooio/_utils/_streams.py
blooio/_utils/_sync.py
blooio/_utils/_transform.py
blooio/_utils/_typing.py
blooio/_utils/_utils.py
blooio/lib/.keep
blooio/resources/__init__.py
blooio/resources/batches.py
blooio/resources/contacts.py
blooio/resources/me.py
blooio/resources/messages.py
blooio/resources/config/__init__.py
blooio/resources/config/config.py
blooio/resources/config/webhook.py
blooio/types/__init__.py
blooio/types/contact_check_capabilities_response.py
blooio/types/me_retrieve_response.py
blooio/types/message_cancel_response.py
blooio/types/message_get_status_response.py
blooio/types/message_retrieve_response.py
blooio/types/message_send_params.py
blooio/types/message_send_response.py
blooio/types/config/__init__.py
blooio/types/config/webhook_retrieve_response.py
blooio/types/config/webhook_update_params.py
blooio/types/config/webhook_update_response.py
blooio-1.0.5.dist-info/METADATA
blooio-1.0.5.dist-info/WHEEL
blooio-1.0.5.dist-info/licenses/LICENSE
blooio-1.0.5.dist-info/RECORD
